solscan_mcp_server/__init__.py
solscan_mcp_server/__main__.py
solscan_mcp_server/server.py
solscan_mcp_server-0.1.0.dist-info/METADATA
solscan_mcp_server-0.1.0.dist-info/WHEEL
solscan_mcp_server-0.1.0.dist-info/entry_points.txt
solscan_mcp_server-0.1.0.dist-info/RECORD
