Metadata-Version: 2.4
Name: solscan-mcp-server
Version: 0.1.0
Summary: A Model Context Protocol server providing tools to interact with the Solscan Pro API via LLMs
Author: Bobby Battista
License: MIT
Keywords: automation,llm,mcp,solana,solscan
Classifier: Development Status :: 4 - Beta
Classifier: Intended Audience :: Developers
Classifier: License :: OSI Approved :: MIT License
Classifier: Programming Language :: Python :: 3
Classifier: Programming Language :: Python :: 3.10
Requires-Python: >=3.10
Requires-Dist: aiohttp>=3.9.0
Requires-Dist: click>=8.1.7
Requires-Dist: mcp>=1.0.0
Requires-Dist: pydantic>=2.0.0
Provides-Extra: dev
Requires-Dist: pyright>=1.1.389; extra == 'dev'
Requires-Dist: pytest-asyncio>=0.23.0; extra == 'dev'
Requires-Dist: pytest>=8.0.0; extra == 'dev'
Requires-Dist: ruff>=0.7.3; extra == 'dev'
